json_logging/__init__.py
json_logging/dto.py
json_logging/formatters.py
json_logging/framework_base.py
json_logging/frameworks.py
json_logging/util.py
json_logging/framework/__init__.py
json_logging/framework/connexion/__init__.py
json_logging/framework/fastapi/__init__.py
json_logging/framework/fastapi/implementation.py
json_logging/framework/flask/__init__.py
json_logging/framework/quart/__init__.py
json_logging/framework/sanic/__init__.py
json_logging-1.5.1.dist-info/LICENSE
json_logging-1.5.1.dist-info/METADATA
json_logging-1.5.1.dist-info/WHEEL
json_logging-1.5.1.dist-info/top_level.txt
json_logging-1.5.1.dist-info/RECORD
