Metadata-Version: 2.1
Name: json-logging
Version: 1.5.1
Summary: JSON Python Logging
Home-page: https://github.com/thangbn/json-logging
Author: Bob T.
License: Apache License 2.0
Keywords: json,elastic,python,python3,python2,logging,logging-library,json,elasticsearch,elk,elk-stack,logstash,kibana
Platform: any
Classifier: Development Status :: 5 - Production/Stable
Classifier: Intended Audience :: Developers
Classifier: License :: OSI Approved :: Apache Software License
Classifier: Operating System :: OS Independent
Classifier: Programming Language :: Python
Classifier: Programming Language :: Python :: 2
Classifier: Programming Language :: Python :: 3
Classifier: Topic :: System :: Logging
Classifier: Framework :: Flask
License-File: LICENSE
